{
	"configurations" : 
	[
		{
			"directories" : 
			[
				{
					"build" : ".",
					"jsonFile" : "directory-.-Release-f5ebdc15457944623624.json",
					"minimumCMakeVersion" : 
					{
						"string" : "3.30"
					},
					"projectIndex" : 0,
					"source" : ".",
					"targetIndexes" : 
					[
						0
					]
				}
			],
			"name" : "Release",
			"projects" : 
			[
				{
					"directoryIndexes" : 
					[
						0
					],
					"name" : "L3",
					"targetIndexes" : 
					[
						0
					]
				}
			],
			"targets" : 
			[
				{
					"directoryIndex" : 0,
					"id" : "L3::@6890427a1f51a3e7e1df",
					"jsonFile" : "target-L3-Release-e9660d67a1c3a8aaab40.json",
					"name" : "L3",
					"projectIndex" : 0
				}
			]
		}
	],
	"kind" : "codemodel",
	"paths" : 
	{
		"build" : "/media/toni/stuff/TUCN/UTCN/Second_Year/II/ECG/Lab/L3/L3/cmake-build-release",
		"source" : "/media/toni/stuff/TUCN/UTCN/Second_Year/II/ECG/Lab/L3/L3"
	},
	"version" : 
	{
		"major" : 2,
		"minor" : 7
	}
}
